{
  "setup": {
    "dataset": "CIFAR-100",
    "pair": "ResNet-56->ResNet-20",
    "N": 10000,
    "seeds": 3,
    "budgets": [
      1000,
      2000,
      4000
    ],
    "teacher_test_acc": 0.7094
  },
  "E3": {
    "1000": {
      "KD": {
        "RGA_KD": {
          "acc_mean": 0.14923333333333333,
          "acc_std": 0.006247310532452255
        },
        "EL2N": {
          "acc_mean": 0.12486666666666667,
          "acc_std": 0.007296726815649754
        },
        "random": {
          "acc_mean": 0.16566666666666666,
          "acc_std": 0.004331538089665404
        },
        "RGA_advantage_over_best_baseline": -0.016433333333333328
      },
      "CE": {
        "RGA_KD": {
          "acc_mean": 0.1252,
          "acc_std": 0.004907137658554122
        },
        "EL2N": {
          "acc_mean": 0.0867,
          "acc_std": 0.006293382768167427
        },
        "random": {
          "acc_mean": 0.12696666666666667,
          "acc_std": 0.002819377393838735
        },
        "RGA_advantage_over_best_baseline": -0.0017666666666666664
      }
    },
    "2000": {
      "KD": {
        "RGA_KD": {
          "acc_mean": 0.2582,
          "acc_std": 0.01764312897419277
        },
        "EL2N": {
          "acc_mean": 0.21109999999999998,
          "acc_std": 0.01511820095117141
        },
        "random": {
          "acc_mean": 0.25593333333333335,
          "acc_std": 0.006138584708401609
        },
        "RGA_advantage_over_best_baseline": 0.002266666666666639
      },
      "CE": {
        "RGA_KD": {
          "acc_mean": 0.2189,
          "acc_std": 0.015481817292122613
        },
        "EL2N": {
          "acc_mean": 0.14713333333333334,
          "acc_std": 0.015954170475319475
        },
        "random": {
          "acc_mean": 0.19720000000000001,
          "acc_std": 0.013972353655224548
        },
        "RGA_advantage_over_best_baseline": 0.021699999999999997
      }
    },
    "4000": {
      "KD": {
        "RGA_KD": {
          "acc_mean": 0.423,
          "acc_std": 0.00793767388260986
        },
        "EL2N": {
          "acc_mean": 0.3567333333333333,
          "acc_std": 0.018914250947073982
        },
        "random": {
          "acc_mean": 0.4019333333333333,
          "acc_std": 0.01746736639819778
        },
        "RGA_advantage_over_best_baseline": 0.021066666666666678
      },
      "CE": {
        "RGA_KD": {
          "acc_mean": 0.34223333333333333,
          "acc_std": 0.0034701905167039584
        },
        "EL2N": {
          "acc_mean": 0.23316666666666666,
          "acc_std": 0.008328398538868215
        },
        "random": {
          "acc_mean": 0.30856666666666666,
          "acc_std": 0.01120307497470623
        },
        "RGA_advantage_over_best_baseline": 0.03366666666666668
      }
    }
  },
  "wall_clock_sec": 535.5390367507935
}